[{"ID":52439,"post_title":"Phang Nga Bay Sunset Serenity Cruise","url":"https:\/\/www.khaolaklanddiscovery.com\/khao-lak-tours\/phang-nga-bay-sunset-serenity-cruise\/"},{"ID":49149,"post_title":"Khao Sok National Park 3 Days Discovery Tour","url":"https:\/\/www.khaolaklanddiscovery.com\/khao-lak-tours\/khao-sok-national-park-3-days-discovery-tour\/"},{"ID":47914,"post_title":"Cheow Lan Lake Adventure | Stay in Khao Sok Floating Bungalows","url":"https:\/\/www.khaolaklanddiscovery.com\/khao-lak-tours\/cheow-lan-lake-khao-sok-floating-bungalows-tour\/"},{"ID":37796,"post_title":"Krabi 4 Island Early Bird Tour - Island Hopping Tour to 4 Breathtaking Krabi Islands!","url":"https:\/\/www.khaolaklanddiscovery.com\/khao-lak-tours\/krabi-islands-tour\/"},{"ID":28139,"post_title":"Phuket Sunday Walking Street - Explore Phuket's Fantastic and Unique Shopping Scene!","url":"https:\/\/www.khaolaklanddiscovery.com\/khao-lak-tours\/phuket-sunday-walking-street-market\/"},{"ID":28002,"post_title":"Khao Sok Jungle Trek - discover the magic of the rainforest","url":"https:\/\/www.khaolaklanddiscovery.com\/khao-lak-tours\/khao-sok-jungle-trekking-tour\/"},{"ID":27793,"post_title":"Takua Pa Old Town and Little Amazon - An Intriguing Journey Through Time and Nature","url":"https:\/\/www.khaolaklanddiscovery.com\/khao-lak-tours\/takua-pa-old-town-and-little-amazon\/"},{"ID":16371,"post_title":"Phuket Tour DIY","url":"https:\/\/www.khaolaklanddiscovery.com\/khao-lak-tours\/phuket-tour-diy\/"},{"ID":16352,"post_title":"Patong Nightlife - Explore the Wild Party Scene in Patong at Night","url":"https:\/\/www.khaolaklanddiscovery.com\/khao-lak-tours\/patong-nightlife\/"},{"ID":16321,"post_title":"Phuket Weekend Market - Explore Phuket's Largest Night Market and Visit Phuket's Big Buddha","url":"https:\/\/www.khaolaklanddiscovery.com\/khao-lak-tours\/phuket-weekend-market\/"},{"ID":16299,"post_title":"Phuket Shopping & Sightseeing - Visit Phuket's Largest Temple and Shop Until You Drop!","url":"https:\/\/www.khaolaklanddiscovery.com\/khao-lak-tours\/phuket-shopping-sightseeing\/"},{"ID":16271,"post_title":"Amazing 3 Temples - Full Day Temple Tour from Khao Lak","url":"https:\/\/www.khaolaklanddiscovery.com\/khao-lak-tours\/amazing-three-temple-tour\/"},{"ID":16255,"post_title":"James Bond Island &  Phang Nga Bay - Breathtakingly Beautiful Ao Phang Nga National Park!","url":"https:\/\/www.khaolaklanddiscovery.com\/khao-lak-tours\/james-bond-island\/"},{"ID":16248,"post_title":"Khao Sok 3 Day Discovery - The Perfect Blend of Khao Sok Wildlife and Luxury!","url":"https:\/\/www.khaolaklanddiscovery.com\/?post_type=st_tours&p=16248"},{"ID":16171,"post_title":"Khao Sok Treehouse 2 Day Discovery- Experience Stunning Khao Sok Natural","url":"https:\/\/www.khaolaklanddiscovery.com\/khao-lak-tours\/khao-sok-treehouse-2-day-discovery-tour\/"},{"ID":15168,"post_title":"Khao Sok Lake Day Trip - Breathtaking Cheow Lan Lake","url":"https:\/\/www.khaolaklanddiscovery.com\/khao-lak-tours\/khao-sok-lake-day-trip\/"},{"ID":15166,"post_title":"Khao Sok Day Trip - Wet and Wild Fun for All Ages!","url":"https:\/\/www.khaolaklanddiscovery.com\/khao-lak-tours\/khao-sok-day-trip\/"},{"ID":15162,"post_title":"Khao Lak Adventure - 3 Thrilling Action Sport Activities!","url":"https:\/\/www.khaolaklanddiscovery.com\/khao-lak-tours\/khao-lak-adventure\/"},{"ID":14791,"post_title":"Khao Lak Elephant Bath  - Exciting Fun for All Ages!","url":"https:\/\/www.khaolaklanddiscovery.com\/khao-lak-tours\/khao-lak-elephant-bath\/"},{"ID":14790,"post_title":"Phi Phi Islands - An Unforgettable Phi Phi Islands Day Trip from Khao Lak","url":"https:\/\/www.khaolaklanddiscovery.com\/khao-lak-tours\/phi-phi-islands-snorkelling-tour\/"},{"ID":14789,"post_title":"Surin Islands Snorkeling Day Trip - Spectacular Marine Life","url":"https:\/\/www.khaolaklanddiscovery.com\/khao-lak-tours\/surin-islands-snorkeling\/"},{"ID":14761,"post_title":"Hong Island & Phang Nga Bay - Exclusive 3 Island Tour at Phang Nga Bay!","url":"https:\/\/www.khaolaklanddiscovery.com\/khao-lak-tours\/hong-island-phang-nga\/"},{"ID":14755,"post_title":"Khao Lak National Park Safari - Bamboo Rafting and Elephant activity, Fun for All Ages!","url":"https:\/\/www.khaolaklanddiscovery.com\/khao-lak-tours\/khao-lak-national-park-safari\/"},{"ID":14625,"post_title":"Similan Islands Snorkeling Day Trip - 9 Islands of Unparalleled Beauty!","url":"https:\/\/www.khaolaklanddiscovery.com\/khao-lak-tours\/similan-islands-snorkeling-day-trip\/"},{"ID":14583,"post_title":"2 Day Khao Sok Wildlife - A Fascinating Cheow Lan Lake Wildlife Spotting Adventure","url":"https:\/\/www.khaolaklanddiscovery.com\/khao-lak-tours\/khao-sok-wildlife\/"},{"ID":14528,"post_title":"Khao Lak Off-Road Safari - Exclusive 4x4 Khao Lak Off-Road Adventure","url":"https:\/\/www.khaolaklanddiscovery.com\/khao-lak-tours\/khao-lak-off-road-safari\/"}]